yousub/__init__.py
yousub/__main__.py
yousub/models.py
yousub/options.py
yousub/tools.py
yousub-0.0.1.dist-info/LICENSE
yousub-0.0.1.dist-info/METADATA
yousub-0.0.1.dist-info/WHEEL
yousub-0.0.1.dist-info/entry_points.txt
yousub-0.0.1.dist-info/top_level.txt
yousub-0.0.1.dist-info/RECORD
