Metadata-Version: 2.1
Name: yousub
Version: 0.0.1
Summary: Download subtitles from YouTube
Home-page: https://github.com/sinb/yousub
Author: sinb
Author-email: si.nb@foxmail.com
License: MIT
Platform: any
Classifier: Programming Language :: Python :: 3
Classifier: License :: OSI Approved :: MIT License
Classifier: Operating System :: OS Independent
